djangocircle/__init__.py
djangocircle/django_response_formatter/__init__.py
djangocircle/django_response_formatter/middleware.py
django_response_formatter-0.1.0.dist-info/LICENSE
django_response_formatter-0.1.0.dist-info/METADATA
django_response_formatter-0.1.0.dist-info/WHEEL
django_response_formatter-0.1.0.dist-info/top_level.txt
django_response_formatter-0.1.0.dist-info/RECORD
