Metadata-Version: 2.1
Name: django-response-formatter
Version: 0.1.0
Summary: A package which returns the common format of response.
Home-page: UNKNOWN
Author: Django Circle
Author-email: djangocircle@gmail.com
License: UNKNOWN
Platform: UNKNOWN
Classifier: Programming Language :: Python :: 3
Classifier: License :: OSI Approved :: MIT License
Classifier: Operating System :: OS Independent
Requires-Python: >=3
Requires-Dist: django (>=2.2.12)
Requires-Dist: djangorestframework (>=3.11.0)
